simplefhe/__init__.py
simplefhe/datatypes.py
simplefhe/decryptors.py
simplefhe/encryptors.py
simplefhe-1.3.3.dist-info/LICENSE
simplefhe-1.3.3.dist-info/METADATA
simplefhe-1.3.3.dist-info/WHEEL
simplefhe-1.3.3.dist-info/top_level.txt
simplefhe-1.3.3.dist-info/RECORD
