Metadata-Version: 2.1
Name: simplefhe
Version: 1.3.3
Summary: Dead-simple full homomorphic encryption (FHE) for Python
Home-page: https://github.com/wgxli/simple-fhe
Author: Samuel Li
Author-email: simplefhe@samuelj.li
License: MIT
Platform: UNKNOWN
Classifier: License :: OSI Approved :: MIT License
Classifier: Programming Language :: Python :: 3
Classifier: Programming Language :: Python :: 3.9
